pure_utils/__init__.py
pure_utils/common.py
pure_utils/containers.py
pure_utils/debug.py
pure_utils/profiler.py
pure_utils/repeaters.py
pure_utils/strings.py
pure_utils/system.py
pure_utils/times.py
pure_utils/types.py
pure_utils-0.9.2.dist-info/LICENSE
pure_utils-0.9.2.dist-info/METADATA
pure_utils-0.9.2.dist-info/WHEEL
pure_utils-0.9.2.dist-info/top_level.txt
pure_utils-0.9.2.dist-info/RECORD
