Metadata-Version: 2.1
Name: pure-utils
Version: 0.9.2
Summary: Yet another python utilities library for collecting useful bicycles and crutches in one place.
Author-email: Peter Bro <p3t3rbr0@gmail.com>
Project-URL: Homepage, https://git.peterbro.su/peter/py3-pure-utils
Project-URL: Documentation, https://pages.peterbro.su/py3-pure-utils/
Project-URL: Repository, https://git.peterbro.su/peter/py3-pure-utils.git
Project-URL: Issues, https://git.peterbro.su/peter/py3-pure-utils/issues
Project-URL: Changelog, https://pages.peterbro.su/py3-pure-utils/changelog.html
Keywords: utilities,bicycle,crutches
Classifier: Development Status :: 5 - Production/Stable
Classifier: Intended Audience :: Developers
Classifier: Operating System :: OS Independent
Classifier: License :: OSI Approved :: MIT License
Classifier: Topic :: Utilities
Classifier: Topic :: Software Development :: Libraries :: Python Modules
Classifier: Programming Language :: Python :: 3
Classifier: Programming Language :: Python :: 3.10
Classifier: Programming Language :: Python :: 3.11
Classifier: Programming Language :: Python :: 3.12
Classifier: Programming Language :: Python :: 3.13
Classifier: Typing :: Typed
Requires-Python: >=3.10
License-File: LICENSE
Provides-Extra: build
Requires-Dist: build ==1.2.2.post1 ; extra == 'build'
Requires-Dist: twine ==5.1.1 ; extra == 'build'
Provides-Extra: dev
Requires-Dist: mypy ==1.13.0 ; extra == 'dev'
Requires-Dist: isort ==5.13.2 ; extra == 'dev'
Requires-Dist: flake8 ==7.1.1 ; extra == 'dev'
Requires-Dist: black ==24.10.0 ; extra == 'dev'
Requires-Dist: pydocstyle ==6.3.0 ; extra == 'dev'
Requires-Dist: pytest ==8.3.3 ; extra == 'dev'
Requires-Dist: pytest-cov ==5.0.0 ; extra == 'dev'
Requires-Dist: pytest-mock ==3.14.0 ; extra == 'dev'
Provides-Extra: docs
Requires-Dist: Sphinx ==8.1.3 ; extra == 'docs'
Requires-Dist: furo ==2024.8.6 ; extra == 'docs'
